fitz_old/libmupdf.dylib
PyMuPDFb-1.23.9rc2.dist-info/RECORD
PyMuPDFb-1.23.9rc2.dist-info/WHEEL
PyMuPDFb-1.23.9rc2.dist-info/README.md
PyMuPDFb-1.23.9rc2.dist-info/COPYING
PyMuPDFb-1.23.9rc2.dist-info/METADATA
fitz/libmupdfcpp.so
fitz/libmupdf.dylib
